{
	"name": "Another Auto Level",
	"description": "",
	"settings": {
		"colorbg": [0, 125, 255],
		"colorground": [0, 125, 255],
		"gamemode": "cube",
		"platformer": false
	},
	"objects": [
		{"type": "block.basic-block", "data": {"x": 0, "y": 2, "rotation": 0, "groups": []}},
		{"type": "block.basic-block", "data": {"x": 0, "y": 1, "rotation": 0, "groups": []}},
		{"type": "block.basic-block", "data": {"x": 1, "y": 1, "rotation": 0, "groups": []}},
		{"type": "portal.gravity-up", "data": {"x": 2, "y": 1, "rotation": 0, "groups": []}},
		{"type": "jump.pad.jump", "data": {"x": 3.5, "y": 3, "rotation": 180, "groups": []}},
		{"type": "portal.gravity-down", "data": {"x": 5, "y": 0, "rotation": 90, "groups": []}},
		{"type": "jump.pad.jump", "data": {"x": 5, "y": 0, "rotation": 0, "groups": []}},
		{"type": "jump.pad.jump", "data": {"x": 7, "y": 2, "rotation": 0, "groups": []}},
		{"type": "jump.pad.jump", "data": {"x": 9, "y": 3, "rotation": 0, "groups": []}},
		{"type": "portal.gamemode.ship", "data": {"x": 11, "y": 1, "rotation": 90, "groups": []}},
		{"type": "jump.pad.gravity", "data": {"x": 15, "y": 0, "rotation": 0, "groups": []}},
		{"type": "portal.gamemode.ball", "data": {"x": 17, "y": 5, "rotation": 270, "groups": []}},
		{"type": "portal.gamemode.cube", "data": {"x": 18, "y": 11, "rotation": 270, "groups": []}},
		{"type": "portal.gravity-down", "data": {"x": 18, "y": 13, "rotation": 270, "groups": []}},
		{"type": "portal.gamemode.wave", "data": {"x": 23, "y": 11, "rotation": 90, "groups": []}},
		{"type": "portal.gamemode.ball", "data": {"x": 27, "y": 8, "rotation": 0, "groups": []}},
		{"type": "block.basic-block", "data": {"x": 20, "y": 14, "rotation": 0, "groups": []}},
		{"type": "block.basic-block", "data": {"x": 20, "y": 13, "rotation": 0, "groups": []}},
		{"type": "block.basic-block", "data": {"x": 20, "y": 12, "rotation": 0, "groups": []}},
		{"type": "block.basic-block", "data": {"x": 20, "y": 11, "rotation": 0, "groups": []}},
		{"type": "block.basic-block", "data": {"x": 20, "y": 10, "rotation": 0, "groups": []}},
		{"type": "block.basic-block", "data": {"x": 20, "y": 9, "rotation": 0, "groups": []}},
		{"type": "block.basic-block", "data": {"x": 20, "y": 8, "rotation": 0, "groups": []}},
		{"type": "block.basic-block", "data": {"x": 20, "y": 7, "rotation": 0, "groups": []}},
		{"type": "block.basic-block", "data": {"x": 20, "y": 6, "rotation": 0, "groups": []}},
		{"type": "block.basic-block", "data": {"x": 20, "y": 5, "rotation": 0, "groups": []}},
		{"type": "block.basic-block", "data": {"x": 20, "y": 4, "rotation": 0, "groups": []}},
		{"type": "block.basic-block", "data": {"x": 20, "y": 3, "rotation": 0, "groups": []}},
		{"type": "block.basic-block", "data": {"x": 20, "y": 2, "rotation": 0, "groups": []}},
		{"type": "block.basic-block", "data": {"x": 20, "y": 1, "rotation": 0, "groups": []}},
		{"type": "block.basic-block", "data": {"x": 20, "y": 0, "rotation": 0, "groups": []}},
		{"type": "block.basic-block", "data": {"x": 0, "y": 3, "rotation": 0, "groups": []}},
		{"type": "block.basic-block", "data": {"x": 0, "y": 4, "rotation": 0, "groups": []}},
		{"type": "block.basic-block", "data": {"x": 0, "y": 5, "rotation": 0, "groups": []}},
		{"type": "block.basic-block", "data": {"x": 1, "y": 5, "rotation": 0, "groups": []}},
		{"type": "block.basic-block", "data": {"x": 2, "y": 5, "rotation": 0, "groups": []}},
		{"type": "block.basic-block", "data": {"x": 3, "y": 5, "rotation": 0, "groups": []}},
		{"type": "block.basic-block", "data": {"x": 4, "y": 5, "rotation": 0, "groups": []}},
		{"type": "block.half-block", "data": {"x": 3.25, "y": 4, "rotation": 90, "groups": []}},
		{"type": "block.half-block", "data": {"x": 3.75, "y": 4, "rotation": 270, "groups": []}},
		{"type": "block.half-block", "data": {"x": 3.5, "y": 4, "rotation": 180, "groups": []}},
		{"type": "death.basic-spike", "data": {"x": 1, "y": 2, "rotation": 90, "groups": []}},
		{"type": "death.basic-spike", "data": {"x": 1, "y": 3, "rotation": 90, "groups": []}},
		{"type": "death.basic-spike", "data": {"x": 1, "y": 4, "rotation": 90, "groups": []}},
		{"type": "death.basic-spike", "data": {"x": 2, "y": 4, "rotation": 180, "groups": []}},
		{"type": "block.basic-block", "data": {"x": 5, "y": 5, "rotation": 0, "groups": []}},
		{"type": "death.basic-spike", "data": {"x": 5, "y": 4, "rotation": 180, "groups": []}},
		{"type": "block.basic-block", "data": {"x": 6, "y": 5, "rotation": 0, "groups": []}},
		{"type": "block.basic-block", "data": {"x": 12, "y": 5, "rotation": 0, "groups": []}},
		{"type": "block.basic-block", "data": {"x": 12, "y": 4, "rotation": 0, "groups": []}},
		{"type": "block.basic-block", "data": {"x": 12, "y": 3, "rotation": 0, "groups": []}},
		{"type": "block.basic-block", "data": {"x": 12, "y": 2, "rotation": 0, "groups": []}},
		{"type": "block.basic-block", "data": {"x": 13, "y": 1, "rotation": 0, "groups": []}},
		{"type": "death.basic-spike", "data": {"x": 16, "y": 0, "rotation": 0, "groups": []}},
		{"type": "death.basic-spike", "data": {"x": 17, "y": 0, "rotation": 0, "groups": []}},
		{"type": "death.basic-spike", "data": {"x": 18, "y": 0, "rotation": 0, "groups": []}},
		{"type": "death.basic-spike", "data": {"x": 19, "y": 0, "rotation": 0, "groups": []}},
		{"type": "block.basic-block", "data": {"x": 7, "y": 6, "rotation": 0, "groups": []}},
		{"type": "block.basic-block", "data": {"x": 8, "y": 7, "rotation": 0, "groups": []}},
		{"type": "block.basic-block", "data": {"x": 9, "y": 8, "rotation": 0, "groups": []}},
		{"type": "block.basic-block", "data": {"x": 10, "y": 7, "rotation": 0, "groups": []}},
		{"type": "block.basic-block", "data": {"x": 11, "y": 6, "rotation": 0, "groups": []}},
		{"type": "block.basic-block", "data": {"x": 21, "y": 10, "rotation": 0, "groups": []}},
		{"type": "block.basic-block", "data": {"x": 22, "y": 9, "rotation": 0, "groups": []}},
		{"type": "block.basic-block", "data": {"x": 23, "y": 8, "rotation": 0, "groups": []}},
		{"type": "block.basic-block", "data": {"x": 24, "y": 7, "rotation": 0, "groups": []}},
		{"type": "block.basic-block", "data": {"x": 25, "y": 6, "rotation": 0, "groups": []}},
		{"type": "block.basic-block", "data": {"x": 26, "y": 5, "rotation": 0, "groups": []}},
		{"type": "block.basic-block", "data": {"x": 29, "y": 5, "rotation": 0, "groups": []}},
		{"type": "block.basic-block", "data": {"x": 29, "y": 6, "rotation": 0, "groups": []}},
		{"type": "block.basic-block", "data": {"x": 29, "y": 7, "rotation": 0, "groups": []}},
		{"type": "block.basic-block", "data": {"x": 29, "y": 8, "rotation": 0, "groups": []}},
		{"type": "block.basic-block", "data": {"x": 29, "y": 9, "rotation": 0, "groups": []}},
		{"type": "block.basic-block", "data": {"x": 28, "y": 10, "rotation": 0, "groups": []}},
		{"type": "death.basic-spike", "data": {"x": 21, "y": 11, "rotation": 0, "groups": []}},
		{"type": "death.basic-spike", "data": {"x": 22, "y": 10, "rotation": 0, "groups": []}},
		{"type": "death.basic-spike", "data": {"x": 23, "y": 9, "rotation": 0, "groups": []}},
		{"type": "death.basic-spike", "data": {"x": 24, "y": 8, "rotation": 0, "groups": []}},
		{"type": "death.basic-spike", "data": {"x": 25, "y": 7, "rotation": 0, "groups": []}},
		{"type": "death.basic-spike", "data": {"x": 26, "y": 6, "rotation": 0, "groups": []}},
		{"type": "block.basic-block", "data": {"x": 30, "y": 4, "rotation": 0, "groups": []}}
	],
	"completion": {
		"percentage": 100,
		"coins": []
	},
	"deleted": false
}